setup.py
qlutils/__init__.py
qlutils/qllgetservers.py
qlutils/qllserver.py
qlutils.egg-info/PKG-INFO
qlutils.egg-info/SOURCES.txt
qlutils.egg-info/dependency_links.txt
qlutils.egg-info/entry_points.txt
qlutils.egg-info/requires.txt
qlutils.egg-info/top_level.txt