Metadata-Version: 1.0
Name: qlutils
Version: 0.1.0.11
Summary: QuakeLive Utilities.
Home-page: https://bitbucket.org/fx_/python3-qlutils
Author: Victor Polevoy
Author-email: contact@vpolevoy.com
License: UNKNOWN
Platform: UNKNOWN
